{

    "lastId": 3,
    "products":  [
        {
            "id":1, 
            "name": "",
            "description": "Une fraise",
            "price":4.2 ,
            "origin":null ,
            "category": "Fruit"
        },
        {
            "id":2, 
            "name": "AirFryer",
            "description": "Fricteuse sans huile",
            "price":49.99 ,
            "origin":"France" ,
            "category": "Electro"
        },
{
            "id":3 ,
            "name": "Grille pain",
            "description": null,
            "price":30,
            "origin":"Belgique" ,
            "category": "Electro"
        }
    ]
}